setup.py
chaosgarden/__init__.py
chaosgarden/alicloud/__init__.py
chaosgarden/alicloud/actions.py
chaosgarden/aws/__init__.py
chaosgarden/aws/actions.py
chaosgarden/azure/__init__.py
chaosgarden/azure/actions.py
chaosgarden/garden/__init__.py
chaosgarden/garden/actions.py
chaosgarden/garden/probes.py
chaosgarden/gcp/__init__.py
chaosgarden/gcp/actions.py
chaosgarden/human/__init__.py
chaosgarden/human/actions.py
chaosgarden/k8s/__init__.py
chaosgarden/k8s/actions.py
chaosgarden/k8s/probes.py
chaosgarden/k8s/api/__init__.py
chaosgarden/k8s/api/authenticators.py
chaosgarden/k8s/api/clients.py
chaosgarden/k8s/api/cluster.py
chaosgarden/k8s/probe/__init__.py
chaosgarden/k8s/probe/metrics.py
chaosgarden/k8s/probe/thresholds.py
chaosgarden/k8s/probe/resources/__init__.py
chaosgarden/k8s/probe/resources/generate_resources.py
chaosgarden/k8s/probe/resources/probe_pod.py
chaosgarden/k8s/probe/resources/suicidal_pod.py
chaosgarden/k8s/probe/resources/templated_resources.yaml
chaosgarden/metal/__init__.py
chaosgarden/openstack/__init__.py
chaosgarden/openstack/actions.py
chaosgarden/util/__init__.py
chaosgarden/util/terminator.py
chaosgarden/util/threading.py
chaosgarden/vsphere/__init__.py
chaosgarden/vsphere/actions.py
chaosgarden/vsphere/pchelper.py
chaosgarden-0.2.14.dist-info/LICENSE
chaosgarden-0.2.14.dist-info/METADATA
chaosgarden-0.2.14.dist-info/WHEEL
chaosgarden-0.2.14.dist-info/top_level.txt
chaosgarden-0.2.14.dist-info/RECORD
