Metadata-Version: 2.1
Name: chaosgarden
Version: 0.2.14
Summary: Generic cloud provider zone outage and Kubernetes pod disruption simulations with specific support for Gardener
Home-page: https://github.com/gardener/chaos-engineering
Author: SAP SE
License: License :: OSI Approved :: Apache Software License
Keywords: chaostoolkit,kubernetes,gardener
Platform: AWS
Platform: Azure
Platform: GCP
Platform: OpenStack
Platform: vSphere
Platform: Kubernetes
Platform: Gardener
Requires-Python: >= 3.9
License-File: LICENSE
Requires-Dist: Mako <2,>=1.2.4
Requires-Dist: PyYAML <7,>=6.0
Requires-Dist: aliyun-python-sdk-core <3,>=2.13.36
Requires-Dist: aliyun-python-sdk-ecs <5,>=4.24.30
Requires-Dist: aliyun-python-sdk-vpc <4,>=3.0.33
Requires-Dist: azure-mgmt-network <23,>=22.2.0
Requires-Dist: chaostoolkit-aws <1,>=0.21.2
Requires-Dist: chaostoolkit-azure <1,>=0.11.0
Requires-Dist: chaostoolkit-google-cloud-platform <1,>=0.8.0
Requires-Dist: chaostoolkit-kubernetes <1,>=0.26.3
Requires-Dist: chaostoolkit-lib <2,>=1.33.1
Requires-Dist: chaostoolkit <2,>=1.15.0
Requires-Dist: kubernetes >=28.1.0
Requires-Dist: openstacksdk <2,>=1.0.1
Requires-Dist: python-box <8,>=7.0.0
Requires-Dist: urllib3 <2,>=1.26.14
